.DS_Store
applefy/__init__.py
applefy/detections/__init__.py
applefy/detections/contrast.py
applefy/detections/uncertainty.py
applefy/gaussianity/__init__.py
applefy/gaussianity/residual_tests.py
applefy/statistics/__init__.py
applefy/statistics/bootstrapping.py
applefy/statistics/general.py
applefy/statistics/parametric.py
applefy/utils/__init__.py
applefy/utils/contrast_curve.py
applefy/utils/contrast_grid.py
applefy/utils/fake_planets.py
applefy/utils/file_handling.py
applefy/utils/mc_simulations.py
applefy/utils/photometry.py
applefy/utils/positions.py
applefy/utils/throughput.py
applefy/wrappers/__init__.py
applefy/wrappers/pynpoint.py
applefy/wrappers/vip.py
applefy-0.1.2.dist-info/LICENSE.txt
applefy-0.1.2.dist-info/METADATA
applefy-0.1.2.dist-info/WHEEL
applefy-0.1.2.dist-info/top_level.txt
applefy-0.1.2.dist-info/RECORD
