Metadata-Version: 2.1
Name: applefy
Version: 0.1.2
Summary: applefy: A library to compute detection limits for high contrast imaging of exoplanets
Home-page: https://github.com/markusbonse/applefy.git
Author: Markus Bonse, Timothy Gebhard
Author-email: mbonse@phys.ethz.ch
License: MIT License
Classifier: Programming Language :: Python :: 3
Classifier: Programming Language :: Python :: 3.8
Classifier: Programming Language :: Python :: 3.9
License-File: LICENSE.txt
Requires-Dist: numpy (>=1.18)
Requires-Dist: astropy (>=4.3)
Requires-Dist: pandas (>=1.5)
Requires-Dist: photutils (>=1.3.0)
Requires-Dist: numba (>=0.54)
Requires-Dist: scikit-learn (>=1.0)
Requires-Dist: scipy (>=1.8.0)
Requires-Dist: tqdm (>=4.62.3)
Requires-Dist: h5py (>=3.6)
Provides-Extra: dev
Requires-Dist: furo (>=2022.12.7) ; extra == 'dev'
Requires-Dist: sphinx-rtd-theme (==1.1.1) ; extra == 'dev'
Requires-Dist: sphinx (<6,>=2.1) ; extra == 'dev'
Requires-Dist: myst-parser (~=0.18.1) ; extra == 'dev'
Requires-Dist: nbsphinx (>=0.8.9) ; extra == 'dev'
Requires-Dist: sphinx-copybutton (~=0.5.1) ; extra == 'dev'
Requires-Dist: sphinx-gallery (<=0.10) ; extra == 'dev'
Requires-Dist: twine (~=4.0.2) ; extra == 'dev'
Requires-Dist: IPython (~=8.8.0) ; extra == 'dev'
Requires-Dist: ipywidgets (~=8.0.4) ; extra == 'dev'
Requires-Dist: jupyter-contrib-nbextensions (~=0.7.0) ; extra == 'dev'
Requires-Dist: sphinx-autodoc-typehints (>1.6) ; extra == 'dev'
Provides-Extra: fast_sort
Requires-Dist: parallel-sort (==0.0.3) ; extra == 'fast_sort'
Provides-Extra: plotting
Requires-Dist: seaborn (~=0.12.1) ; extra == 'plotting'
Requires-Dist: matplotlib (>=3.4.3) ; extra == 'plotting'
Requires-Dist: bokeh (>=3.0.3) ; extra == 'plotting'
Provides-Extra: pynpoint
Requires-Dist: pynpoint (>=0.10.0) ; extra == 'pynpoint'
Provides-Extra: vip
Requires-Dist: vip-hci (>=1.5.2) ; extra == 'vip'
Requires-Dist: packaging (>=22.0) ; extra == 'vip'
